tidycode/__init__.py
tidycode/cli/__init__.py
tidycode/cli/commands/__init__.py
tidycode/cli/commands/clean.py
tidycode/cli/commands/commitizen.py
tidycode/cli/commands/configs.py
tidycode/cli/commands/dependabot.py
tidycode/cli/commands/hooks.py
tidycode/cli/commands/quality.py
tidycode/cli/main.py
tidycode/core/__init__.py
tidycode/core/bootstrap/__init__.py
tidycode/core/bootstrap/setup_commitizen.py
tidycode/core/bootstrap/setup_dependabot.py
tidycode/core/bootstrap/setup_hooks.py
tidycode/core/bootstrap/setup_tools.py
tidycode/core/quality_tools.py
tidycode/core/yaml/__init__.py
tidycode/core/yaml/adapters/__init__.py
tidycode/core/yaml/adapters/base.py
tidycode/core/yaml/adapters/pyyaml_adapter.py
tidycode/core/yaml/adapters/ruamel_adapter.py
tidycode/core/yaml/manager.py
tidycode/core/yaml/utils.py
tidycode/utils/__init__.py
tidycode/utils/constants.py
tidycode/utils/helpers.py
tidycode/utils/hooks/__init__.py
tidycode/utils/hooks/hooks_definitions.py
tidycode/utils/hooks/hooks_helpers.py
tidycode/utils/toml/__init__.py
tidycode/utils/toml/toml_config_diff.py
tidycode/utils/toml/toml_config_editor.py
tidycode/utils/toml/toml_helpers.py
tidycode/utils/tools_metadata.py
tidycode-0.1.0.dist-info/METADATA
tidycode-0.1.0.dist-info/WHEEL
tidycode-0.1.0.dist-info/entry_points.txt
tidycode-0.1.0.dist-info/RECORD
