Metadata-Version: 2.3
Name: tidycode
Version: 0.1.0
Summary: Kit minimal pour automatiser le lint, format, type-checking, changelog et hooks dans vos projets Python
Author: Ephraïm SEDDOR
Author-email: seddorephraim7@gmail.com
Requires-Python: >=3.10,<4.0
Classifier: Programming Language :: Python :: 3
Classifier: Programming Language :: Python :: 3.10
Classifier: Programming Language :: Python :: 3.11
Classifier: Programming Language :: Python :: 3.12
Classifier: Programming Language :: Python :: 3.13
Requires-Dist: questionary (>=2.1.0,<3.0.0)
Requires-Dist: ruamel-yaml (>=0.18.14,<0.19.0)
Requires-Dist: tomlkit (>=0.13.3,<0.14.0)
Requires-Dist: typer[all] (>=0.16.0,<0.17.0)
